MANIFEST.in
README.md
setup.cfg
setup.py
qasem/__init__.py
qasem/candidates_finder.py
qasem/end_to_end_pipeline.py
qasem/openie_converter.py
qasem/qa_adj_pipeline.py
qasem/qa_discourse_pipeline.py
qasem/question_contextualizer.py
qasem/spacy_loader.py
qasem/test_end_to_end_pipeline.py
qasem/utils.py
qasem/version.txt
qasem.egg-info/PKG-INFO
qasem.egg-info/SOURCES.txt
qasem.egg-info/dependency_links.txt
qasem.egg-info/requires.txt
qasem.egg-info/top_level.txt
qasem/data/connectives_small_set.txt