Metadata-Version: 2.1
Name: qasem
Version: 0.2.0
Summary: package for QA-based Semantics - representing textual information via question-answer pairs
Home-page: https://github.com/kleinay/QASem
Author: Ayal Klein, Ruben Wolhandler, Ron Eliav
Author-email: ayal.s.klein@gmail.com
License: UNKNOWN
Platform: UNKNOWN
Classifier: Programming Language :: Python :: 3
Classifier: License :: OSI Approved :: MIT License
Classifier: Operating System :: OS Independent
Requires-Python: >=3.7
